vinmap/vinmap.py
vinmap/core/__init__.py
vinmap/core/cli.py
vinmap/core/cmd_list.py
vinmap/core/color_codes.py
vinmap/core/threading_classes.py
vinmap/utils/__init__.py
vinmap/utils/file_utils.py
vinmap/utils/html_utils.py
vinmap/utils/ip_utils.py
vinmap/utils/json_utils.py
vinmap/utils/scan_utils.py
vinmap/utils/xml_utils.py
vinmap-1.1.4.dist-info/METADATA
vinmap-1.1.4.dist-info/WHEEL
vinmap-1.1.4.dist-info/entry_points.txt
vinmap-1.1.4.dist-info/top_level.txt
vinmap-1.1.4.dist-info/RECORD
