Metadata-Version: 2.1
Name: vinmap
Version: 1.1.4
Summary: Multithreaded scanner using nmap for scanning allowing you to use python 3.13 with gil disabled,that provides XML Merging and html/json output options.
Home-page: https://github.com/VinnyVanGogh/ViNmap_custom_nmap_scanner
Author: Vince Vasile
Author-email: Vince Vasile <computerscience@vinny-van-gogh.com>
License: MIT
Project-URL: Homepage, https://github.com/VinnyVanGogh/ViNmap_custom_nmap_scanner
Requires-Python: >=3.7
Requires-Dist: python-nmap
Requires-Dist: xmltodict
